MANIFEST.in
README.md
setup.py
netos_inventory/__init__.py
netos_inventory/constants.py
netos_inventory/filtersets.py
netos_inventory/forms.py
netos_inventory/models.py
netos_inventory/navigation.py
netos_inventory/tables.py
netos_inventory/urls.py
netos_inventory/views.py
netos_inventory.egg-info/PKG-INFO
netos_inventory.egg-info/SOURCES.txt
netos_inventory.egg-info/dependency_links.txt
netos_inventory.egg-info/not-zip-safe
netos_inventory.egg-info/top_level.txt
netos_inventory/api/__init__.py
netos_inventory/api/serializers.py
netos_inventory/api/urls.py
netos_inventory/api/views.py
netos_inventory/migrations/0001_initial.py
netos_inventory/migrations/0002_delete_networkfabric.py
netos_inventory/migrations/0003_alter_lanconsolidationreport_options.py
netos_inventory/migrations/__init__.py
netos_inventory/static/netos_inventory/js/bundle.js
netos_inventory/static/netos_inventory/js/lan_report.js
netos_inventory/static/netos_inventory/js/last_detected.js
netos_inventory/templates/netos_inventory/bulk_recon.html
netos_inventory/templates/netos_inventory/bulk_recon_button.html
netos_inventory/templates/netos_inventory/hardware_last_detected.html
netos_inventory/templates/netos_inventory/lan_object_list.html
netos_inventory/templates/netos_inventory/lan_utilization_graph.html
netos_inventory/templates/netos_inventory/logical_last_detected.html
netos_inventory/templates/netos_inventory/object_list_recon.html
netos_inventory/templates/netos_inventory/inc/table_controls_htmx.html
netos_inventory/templatetags/__init__.py
netos_inventory/templatetags/recon_buttons.py