Metadata-Version: 2.1
Name: netos-inventory
Version: 0.2.1
Summary: An reconciliation plugin for NetBox
